figures/__init__.py
figures/line.py
figures/triangle.py
my_geometry_project_yandex_ect-0.11.dist-info/METADATA
my_geometry_project_yandex_ect-0.11.dist-info/WHEEL
my_geometry_project_yandex_ect-0.11.dist-info/top_level.txt
my_geometry_project_yandex_ect-0.11.dist-info/RECORD
