Metadata-Version: 2.1
Name: my-geometry-project-yandex-ect
Version: 0.11
Summary: This is my first package
Home-page: UNKNOWN
Author: DanilFarafonov
Author-email: proverka@lalala.openedu
License: UNKNOWN
Platform: UNKNOWN
